readerlet/__init__.py
readerlet/__main__.py
readerlet/article.py
readerlet/cli.py
readerlet/epub.py
readerlet/mailer.py
readerlet/js/extract_stdout.js
readerlet/js/package.json
readerlet/templates/container.xml
readerlet/templates/content.opf
readerlet/templates/content.xhtml
readerlet/templates/stylesheet.css
readerlet-0.2.3.dist-info/licenses/LICENSE
readerlet-0.2.3.dist-info/METADATA
readerlet-0.2.3.dist-info/WHEEL
readerlet-0.2.3.dist-info/entry_points.txt
readerlet-0.2.3.dist-info/top_level.txt
readerlet-0.2.3.dist-info/RECORD
