Metadata-Version: 2.4
Name: readerlet
Version: 0.2.3
Summary: A command-line utility for extracting and packaging web content for offline reading.
Author: pavzari
License: Apache-2.0
Project-URL: Homepage, https://github.com/pavzari/readerlet
Project-URL: Changelog, https://github.com/pavzari/readerlet/releases
Project-URL: Issues, https://github.com/pavzari/readerlet/issues
Project-URL: CI, https://github.com/pavzari/readerlet/actions
Classifier: License :: OSI Approved :: Apache Software License
Requires-Python: >=3.8
License-File: LICENSE
Requires-Dist: click
Requires-Dist: beautifulsoup4
Requires-Dist: requests
Requires-Dist: stkclient
Requires-Dist: Jinja2
Requires-Dist: pillow
Provides-Extra: test
Requires-Dist: pytest; extra == "test"
Requires-Dist: pytest-subprocess; extra == "test"
Requires-Dist: pytest-cov; extra == "test"
Requires-Dist: ruff; extra == "test"
Provides-Extra: node
Requires-Dist: nodejs-bin[cmd]; extra == "node"
Dynamic: license-file
